foundry_local/__init__.py
foundry_local/api.py
foundry_local/client.py
foundry_local/logging.py
foundry_local/models.py
foundry_local/service.py
foundry_local/version.py
foundry_local_sdk-0.5.0.dist-info/licenses/LICENSE.txt
foundry_local_sdk-0.5.0.dist-info/METADATA
foundry_local_sdk-0.5.0.dist-info/WHEEL
foundry_local_sdk-0.5.0.dist-info/top_level.txt
foundry_local_sdk-0.5.0.dist-info/RECORD
