Metadata-Version: 2.4
Name: foundry-local-sdk
Version: 0.5.0
Summary: Foundry Local Manager Python SDK: Control-plane SDK for Foundry Local.
Author-email: Microsoft Corporation <foundrylocaldevs@microsoft.com>
License: MIT License
Project-URL: Homepage, https://github.com/microsoft/Foundry-Local
Classifier: Development Status :: 3 - Alpha
Classifier: Intended Audience :: Developers
Classifier: Topic :: Scientific/Engineering
Classifier: Topic :: Scientific/Engineering :: Artificial Intelligence
Classifier: Topic :: Software Development
Classifier: Topic :: Software Development :: Libraries
Classifier: Topic :: Software Development :: Libraries :: Python Modules
Classifier: Programming Language :: Python
Classifier: Programming Language :: Python :: 3 :: Only
Classifier: Programming Language :: Python :: 3.9
Classifier: Programming Language :: Python :: 3.10
Classifier: Programming Language :: Python :: 3.11
Classifier: Programming Language :: Python :: 3.12
Classifier: Programming Language :: Python :: 3.13
Requires-Python: >=3.9
License-File: LICENSE.txt
Requires-Dist: httpx
Requires-Dist: pydantic>=2.0.0
Requires-Dist: tqdm
Dynamic: license-file
